
{"id":"143a03ae-4b0e-414c-8bc6-c12cad59674b","name":"TestAPIAudience","description":null,"auth":null,"events":null,"variables":[],"order":["cb48cb9a-54e8-4989-9c09-9118a722aab8","d83d0103-55e5-4fbe-9cd8-5c28388b3862","edfbdc47-e5f2-43b0-af36-ecfe2d999575","03e1ecec-390e-4afa-9f66-931d9a7ec426","2f91f2e6-ad29-44e9-bce7-f21f2a52da7b","d6a74918-e68d-4d44-a586-94aceba9da01"],"folders_order":[],"protocolProfileBehavior":[],"folders":[],"requests":[{"id":"03e1ecec-390e-4afa-9f66-931d9a7ec426","name":"put","url":"http:\/\/localhost:8080\/audience\/5e8b6f403d522a3a48598ac5","description":"","data":[],"dataOptions":{"raw":{"language":"json"}},"dataMode":"raw","headerData":[],"method":"PUT","pathVariableData":[],"queryParams":[],"auth":null,"events":[],"folder":null,"currentHelper":null,"helperAttributes":null,"collectionId":"143a03ae-4b0e-414c-8bc6-c12cad59674b","rawModeData":"{\r\n    \"Nombre\": \"Isabel\",\r\n    \"Apellidos\": \"Lizano de la Pascua\",\r\n    \"DNI\": \"33333333P\",\r\n    \"Edad\": 18\r\n}","headers":"","pathVariables":[]},{"id":"2f91f2e6-ad29-44e9-bce7-f21f2a52da7b","name":"deleteOne","url":"http:\/\/localhost:8080\/audience\/5e8b6f403d522a3a48598ac5","description":"","data":null,"dataOptions":null,"dataMode":null,"headerData":[],"method":"DELETE","pathVariableData":[],"queryParams":[],"auth":null,"events":[],"folder":null,"currentHelper":null,"helperAttributes":null,"collectionId":"143a03ae-4b0e-414c-8bc6-c12cad59674b","headers":"","pathVariables":[]},{"id":"cb48cb9a-54e8-4989-9c09-9118a722aab8","name":"post","url":"http:\/\/localhost:8080\/audience\/","description":"","data":[],"dataOptions":{"raw":{"language":"json"}},"dataMode":"raw","headerData":[],"method":"POST","pathVariableData":[],"queryParams":[],"auth":null,"events":[],"folder":null,"currentHelper":null,"helperAttributes":null,"collectionId":"143a03ae-4b0e-414c-8bc6-c12cad59674b","rawModeData":"{\r\n\t\"Nombre\": \"Prueba POST POSTMAN\",\r\n\t\"Apellidos\": \"del Rio Monta\u00f1es\",\r\n\t\"DNI\": \"55555555K\",\r\n\t\"Edad\": 24\r\n}","headers":"","pathVariables":[]},{"id":"d6a74918-e68d-4d44-a586-94aceba9da01","name":"deleteAll","url":"http:\/\/localhost:8080\/audience\/","description":"","data":null,"dataOptions":null,"dataMode":null,"headerData":[],"method":"DELETE","pathVariableData":[],"queryParams":[],"auth":null,"events":[],"folder":null,"currentHelper":null,"helperAttributes":null,"collectionId":"143a03ae-4b0e-414c-8bc6-c12cad59674b","headers":"","pathVariables":[]},{"id":"d83d0103-55e5-4fbe-9cd8-5c28388b3862","name":"getOne","url":"http:\/\/localhost:8080\/audience\/5e8b6f403d522a3a48598ac5","description":"","data":null,"dataOptions":null,"dataMode":null,"headerData":[],"method":"GET","pathVariableData":[],"queryParams":[],"auth":null,"events":[],"folder":null,"currentHelper":null,"helperAttributes":null,"collectionId":"143a03ae-4b0e-414c-8bc6-c12cad59674b","headers":"","pathVariables":[]},{"id":"edfbdc47-e5f2-43b0-af36-ecfe2d999575","name":"getAll","url":"http:\/\/localhost:8080\/audience\/","description":"","data":null,"dataOptions":null,"dataMode":null,"headerData":[],"method":"GET","pathVariableData":[],"queryParams":[],"auth":null,"events":[],"folder":null,"currentHelper":null,"helperAttributes":null,"collectionId":"143a03ae-4b0e-414c-8bc6-c12cad59674b","headers":"","pathVariables":[]}]}